{"unsalted sunflower seeds": "$3.69", "raspberries": "$3.49", "coconut": "$7.99", "frozen chopped spinach": "$2.99", "cooked chicken": "$7.99", "white sugar": "$3.29", "milk": "$2.19", "heavy cream": "$4.49", "olive oil": "$6.99", "lemon zest": "$0.97", "taco seasoning mix": "$1.99", "avocados": "$3.99", "vegetable stock": "$2.99", "breakfast sausage": "$6.99", "vidalia onion": "$1.53", "chicken broth": "$1.99", "smoked sausage": "$5.99", "lacinato kale": "$1.99", "fresh parsley": "$1.49", "peanuts": "$4.99", "low-fat cottage cheese": "$3.29", "chicken": "$5.99", "baking chocolate": "$6.69", "low sodium soy sauce": "$6.39", "medium shrimp": "$16.99", "coarse ground black pepper": "$7.99", "roasted cashew": "$12.99", "button mushrooms": "$5.99", "chopped cilantro": "$1.49", "canned chickpeas": "$1.49", "fresh parsley leaves": "$1.49", "bittersweet chocolate chips": "$3.99", "ground cayenne": "$3.99", "creamy peanut butter": "$4.99", "grated cheddar": "$4.99", "corn kernels": "$3.99", "broccoli florets": "$3.14", "ice cream": "$3.99", "fresh Parmesan cheese": "$19.99", "red pepper": "$1.02", "minced garlic": "$7.49", "diced tomatoes with juice": "$0.49", "Italian parsley": "$1.49", "seasoned rice vinegar": "$3.69", "mandarin orange segments": "$11.49", "salted butter": "$4.07", "water": "$2.99", "basil pesto": "$12.99", "yellow pepper": "$2.99", "instant rice": "$3.39", "unsweetened almond milk": "$1.89", "chilli powder": "$5.99", "yellow onion": "$1.13", "lemon": "$2.99", "carrots": "$2.99", "reduced sodium soy sauce": "$3.99", "crushed rosemary": "$4.99", "salt": "$9.99", "seasoning salt": "$2.99", "frozen mixed vegetables": "$3.99", "oyster sauce": "$3.19", "beef chuck roast": "$5.99", "almond meal": "$12.79", "smoked paprika": "$9.49", "extra lean ground beef": "$6.99", "feta cheese": "$7.99", "fresh bread crumbs": "$2.89", "cooked chicken breasts": "$6.99", "cheese": "$10.99", "whole milk": "$2.19", "fish fillet": "$7.99", "dried rosemary": "$2.99", "flank steak": "$15.99", "vanilla wafers": "$3.99", "Hass avocado": "$3.99", "beef stew meat": "$6.99", "butter": "$12.99", "cumin": "$1.99", "McCormick Bay Leaves": "$6.99", "vanilla extract": "$17.99", "seasoned salt": "$6.29", "frozen green peas": "$3.99", "red curry paste": "$3.99", "arugula": "$4.69", "spices": "$5.99", "asparagus": "$3.29", "barbecue sauce": "$7.99", "tomato juice": "$2.69", "Hellmanns Deli Mustard": "$1.99", "teriyaki sauce": "$2.99", "hellmann's or best foods real mayonnaise": "$4.99", "sriracha": "$4.99", "cajun seasoning": "$5.69", "tilapia fillets": "$7.99", "velveeta cheese": "$3.99", "freshly grated Parmesan": "$3.99", "pepperoni": "$14.99", "beef": "$6.99", "baking soda": "$0.99", "cabbage": "$2.32", "lasagna noodles, cooked and drained": "$6.99", "coriander seeds": "$3.99", "chipotle chili in adobo sauce": "$2.79", "pork chops": "$8.99", "nutmeg": "$4.99", "okra": "$9.49", "mexican blend cheese": "$3.69", "dark chocolate chips": "$7.99", "cream cheese": "$2.99", "chopped fresh cilantro": "$1.49", "sesame oil": "$4.29", "pasta": "$3.99", "rolled oats": "$0.99", "spaghetti sauce": "$2.29", "canola oil": "$6.29", "Philadelphia Cream Cheese": "$2.99", "part-skim mozzarella cheese": "$5.99", "ground cumin": "$1.99", "virgin olive oil": "$6.99", "tomatoes": "$3.99", "red vinegar white white, wine,": "$2.49", "gochujang": "$4.94", "pasta sauce": "$6.99", "coconut milk": "$3.79", "salmon filet": "$15.99", "nut butter": "$11.99", "hamburger": "$6.99", "herbs": "$2.99", "almond butter": "$14.99", "creole mustard": "$19.99", "walnut pieces": "$6.99", "garlic powder": "$3.99", "sugar": "$7.99", "green onion": "$0.89", "fresh rosemary": "$2.99", "cracked pepper": "$6.29", "coconut aminos": "$6.39", "green pepper": "$1.02", "frozen whole kernel corn": "$1.99", "nonfat greek yogurt": "$5.69", "Daiya": "$4.75", "apple juice": "$7.99", "tomato soup": "$3.60", "fresh mozzarella cheese": "$5.99", "reduced sodium chicken broth": "$1.99", "creole spice mix": "$8.99", "hardboiled eggs": "$4.99", "lime": "$0.49", "allspice": "$3.99", "kielbasa sausage": "$6.99", "ranch dressing mix": "$3.49", "bacon": "$9.99", "tomato sauce": "$5.49", "oat flour": "$11.49", "fresh dill": "$1.49", "full fat cream cheese": "$2.69", "chopped fresh herbs": "$0.75", "taco sauce": "$4.49", "Spring! Water": "$3.49", "vegetable oil": "$7.99", "salmon fillet": "$15.99", "whole grain dijon mustard": "$3.99", "cooked quinoa": "$3.99", "old fashioned oats": "$3.99", "firmly packed dark brown sugar": "$4.99", "low sodium vegetable broth": "$2.99", "purple onion": "$1.17", "shredded Parmesan cheese": "$3.99", "worcestershire sauce": "$2.49", "spaghetti": "$3.99", "red potatoes": "$3.99", "fine sea salt": "$8.99", "diced yellow onion": "$0.63", "molasses": "$6.49", "pie crust": "$6.99", "veggie crumbles": "$4.79", "small carrots": "$2.99", "shredded carrots": "$2.49", "sliced green onions": "$0.63", "dry white wine": "$7.99", "dried thyme leaves": "$2.99", "oregano": "$2.99", "Dijon mustard": "$3.99", "refrigerated pizza dough": "$4.99", "finely chopped onion": "$1.99", "italian sausage": "$4.49", "mayonnaise": "$4.95", "ground ginger": "$3.99", "tomato pur\u00c3\u00a9e": "$6.99", "English cucumber": "$2.49", "black beans": "$0.79", "Dutch cocoa powder": "$8.39", "sweet onion": "$1.53", "petite diced tomatoes": "$1.79", "flat-leaf parsley": "$1.49", "fettuccine": "$3.99", "fat free shredded cheddar cheese": "$5.99", "limes": "$0.49", "boneless beef chuck roast": "$5.99", "mozzarella": "$9.99", "italian seasoned dry bread crumbs": "$2.89", "light mayonnaise": "$3.29", "yellow onions": "$1.13", "sweet potatoes": "$3.99", "firm tofu": "$2.39", "courgette": "$0.80", "powdered sugar": "$4.29", "cayenne pepper sauce": "$4.69", "Skippy Creamy Peanut Butter": "$3.99", "breakfast sausage links": "$6.99", "fresh ginger root": "$1.28", "white, white wine, red vinegar": "$2.49", "paprika": "$2.99", "shrimp": "$16.99", "shredded cheddar cheese": "$10.99", "whole wheat penne": "$3.49", "coconut oil": "$7.99", "shredded sharp cheddar cheese": "$10.99", "McCormick Black Pepper": "$3.99", "salmon filets": "$11.99", "blueberries": "$5.99", "plain greek yogurt": "$5.69", "prepared mustard": "$3.99", "carrot": "$2.99", "turmeric": "$19.99", "chinese black vinegar": "$3.69", "sunflower oil": "$4.99", "roasted cashews": "$12.99", "rice wine vinegar": "$3.69", "veggie ground round": "$4.79", "fish sauce": "$15.99", "creamy italian dressing": "$2.35", "chicken breast": "$3.59", "low-fat Greek yogurt": "$5.69", "green beans": "$2.99", "basmati rice": "$2.79", "grass-fed butter": "$3.99", "jasmine rice": "$2.69", "chopped carrots": "$0.99", "shells": "$5.99", "toasted sesame seeds": "$6.49", "crushed ritz crackers": "$3.29", "old-fashioned oats": "$1.49", "vanilla yogurt": "$1.07", "sea salt flakes": "$6.99", "elbow macaroni": "$0.99", "mccormick black pepper, coarse ground": "$3.99", "Mexican cheese": "$4.99", "day-old challah bread": "$4.99", "red onion": "$0.89", "beef chuck": "$5.99", "granny smith apples": "$1.02", "frozen blueberries": "$15.29", "ranch dressing": "$0.99", "fat free sour cream": "$5.69", "ground cloves": "$5.99", "frozen tater tots": "$3.99", "Thai sweet chili sauce": "$2.99", "canned black beans": "$0.79", "nonfat vanilla greek yogurt": "$0.80", "baking spray": "$4.99", "ragu pasta sauce": "$6.99", "enchilada sauce": "$3.32", "all purpose flour": "$4.99", "sliced almonds": "$4.99", "lemon juice": "$2.49", "marinara sauce": "$9.79", "ramen noodles": "$2.99", "Best Foods Dijonnaise Creamy Dijon Mustard": "$2.85", "cheese tortellini": "$6.49", "2% reduced fat milk": "$5.49", "chopped tomatoes": "$1.79", "2% lowfat greek yogurt": "$5.99", "chicken thighs": "$3.99", "kosher salt": "$6.99", "breadcrumbs": "$2.89", "peeled and deveined shrimp": "$16.99", "Simply Potatoes Shredded Hash Browns": "$3.99", "Worcestershire sauce": "$2.49", "curly leaf parsley": "$1.49", "green peas": "$3.99", "whole kernel corn": "$2.69", "red chilies": "$3.99", "eggs": "$3.99", "miso paste": "$4.69", "cream": "$4.49", "mexican chorizo": "$5.99", "canola": "$7.99", "mushrooms": "$3.99", "cottage cheese": "$5.49", "thyme": "$2.99", "taco seasoning": "$2.99", "chives": "$2.99", "fresh lime": "$0.49", "extra large shrimp": "$16.99", "apple cider vinegar": "$2.99", "sliced mushrooms": "$2.79", "blue cheese": "$4.99", "bbq sauce": "$7.99", "boneless pork chops": "$8.99", "onion": "$1.13", "cooked brown rice": "$2.39", "red lentils": "$2.49", "almonds": "$8.99", "pineapple juice": "$3.99", "tomato": "$0.81", "boneless skinless chicken breast halves": "$5.99", "freshly ground black pepper": "$5.99", "jalape\u00c3\u00b1o peppers": "$3.99", "hot fudge sauce": "$4.99", "flat iron steak": "$11.99", "basil": "$2.99", "pink lentils": "$2.49", "green bell pepper, sliced": "$0.82", "Thai red curry paste": "$1.28", "plain low fat greek yogurt": "$5.69", "sprinkles": "$1.99", "unsalted beef stock": "$6.49", "cauliflower florets": "$3.49", "dried basil": "$4.99", "vanilla ice cream": "$7.99", "gruy\u00c3\u00a8re cheese": "$10.99", "clover honey": "$5.49", "bone-in pork chops": "$8.99", "bread": "$6.99", "tortillas": "$3.99", "sour cream": "$2.39", "sirloin steak": "$13.99", "rice": "$2.69", "colby jack cheese": "$5.29", "ground chicken breast": "$6.99", "ground black pepper": "$2.99", "milk chocolate chips": "$7.99", "egg noodles": "$3.99", "corn starch": "$1.99", "arborio rice": "$2.25", "fresh cracked black pepper": "$5.49", "sundried tomatoes": "$5.29", "chopped green bell pepper": "$4.99", "crumbled feta": "$3.29", "spring mix salad greens": "$4.99", "chili pepper": "$3.99", "plain yogurt": "$2.49", "cream of mushroom soup": "$2.99", "white chocolate chips": "$3.99", "celery ribs": "$1.99", "nonstick cooking spray": "$6.29", "frozen hash brown potatoes": "$3.99", "shallot": "$2.99", "parsley flakes": "$3.99", "sun dried tomatoes": "$5.29", "red bell pepper": "$1.07", "fresh mushrooms": "$2.79", "less sodium soy sauce": "$3.99", "bell pepper": "$0.82", "diced tomatoes with green chilies": "$1.39", "McCormick\u00c2\u00ae Thyme Leaves": "$2.99", "ketchup": "$4.69", "melted butter": "$12.99", "fine grain sea salt": "$8.99", "vegetarian refried beans": "$1.29", "low sodium chicken broth": "$1.99", "large shrimp": "$16.99", "linguine": "$1.39", "vegetable broth": "$4.69", "fresh spinach leaves": "$4.69", "salt and ground black pepper": "$5.99", "hash browns": "$4.79", "chia seeds": "$7.99", "knorr pasta sides - stroganoff": "$3.99", "rice vinegar": "$7.99", "Chinese rice wine": "$9.99", "hellmann' or best food real mayonnais": "$4.99", "chopped pecans": "$5.99", "oranges": "$4.99", "frozen corn": "$2.69", "macaroni": "$4.19", "vegetarian Worcestershire sauce": "$2.49", "breakfast sausage patties": "$4.99", "refrigerated crescent dinner rolls": "$3.99", "Sriracha sauce": "$7.99", "zucchini": "$0.80", "butter cooking spray": "$9.99", "promise buttery spread": "$4.99", "yellow mustard": "$1.89", "plain low fat yogurt": "$3.49", "Hellmann's\u00c2\u00ae or Best Foods\u00c2\u00ae Light Mayonnaise": "$4.95", "extract": "$4.99", "jalapeno": "$3.99", "Italian bread crumbs": "$2.89", "pepperjack cheese": "$7.99", "white bread": "$4.99", "fresh spinach": "$4.69", "onion powder": "$2.99", "cooking spray": "$6.29", "salmon fillets": "$11.99", "skinless chicken breasts": "$5.99", "plain flour": "$2.69", "grated Parmesan": "$11.99", "tortilla strips": "$2.99", "loosely packed fresh basil leaves": "$1.49", "red pepper flakes": "$3.99", "grape tomatoes": "$2.99", "cracked black pepper": "$6.99", "mozzarella cheese": "$9.99", "black pepper": "$2.99", "Old Bay Seasoning": "$4.99", "skippy creamy peanut butter": "$3.99", "grated cheddar cheese": "$4.99", "pecorino romano": "$14.99", "rice noodles": "$4.04", "pork chops, 1-inch thick": "$4.99", "balsamic vinegar": "$8.99", "i can't believe it's not butter! spread": "$4.99", "sea salt": "$2.69", "white wine": "$2.99", "lime wedges": "$3.99", "red wine": "$34.99", "Old Bay": "$4.99", "heavy whipping cream": "$4.49", "fresh thyme leaves": "$2.99", "light brown sugar": "$3.79", "yukon gold potato": "$0.54", "peppermint extract": "$4.99", "scallions": "$0.89", "ginger": "$1.28", "spinach": "$4.69", "lime zest": "$27.99", "shredded mozzarella cheese": "$9.99", "cayenne pepper": "$4.99", "greens": "$7.99", "graham crackers": "$3.29", "flour": "$3.29", "green peppers": "$1.02", "vegetables": "$12.99", "celery": "$6.95", "orange pepper": "$1.02", "coarse salt": "$1.99", "panko": "$5.49", "red beans": "$4.49", "cucumber": "$0.79", "fresh Italian parsley": "$1.49", "honey": "$9.49", "dry bread crumbs": "$2.89", "yellow bell pepper": "$0.82", "cayenne": "$6.29", "green lentils": "$3.49", "bacon bits": "$6.99", "chive and onion cream cheese spread": "$6.99", "basil leaves": "$2.99", "softened butter": "$3.99", "crimini mushrooms": "$5.99", "sherbet": "$5.49", "light soy sauce": "$3.99", "Jagermeister Liqueur": "$20.99", "tomato paste": "$0.79", "mustard": "$1.89", "pepper": "$7.99", "panko bread crumbs": "$2.89", "banana": "$0.19", "chopped garlic": "$2.79", "Country Crock\u00c2\u00ae Spread": "$4.99", "ground coriander": "$1.99", "fresh tarragon": "$3.99", "Canadian bacon": "$6.99", "fresh chives": "$2.99", "kalamata olives": "$3.29", "avocado": "$3.99", "pure maple syrup": "$7.99", "spicy Italian sausage": "$6.99", "soft corn tortillas": "$1.99", "lump crabmeat": "$17.99", "low sodium beef broth": "$1.99", "frozen raspberries": "$6.69", "baby greens": "$3.99", "raisins": "$4.99", "ground turmeric": "$2.99", "2% milk": "$3.49", "chopped onion": "$1.13", "seasoning": "$4.99", "cheddar cheese": "$11.99", "cilantro leaves": "$0.79", "condensed cream of mushroom soup": "$6.29", "celery stalks": "$1.99", "yellow curry powder": "$5.49", "burrito size flour tortillas": "$2.69", "margarine": "$3.99", "frozen broccoli florets": "$3.14", "skin on salmon fillet": "$9.99", "baby broccoli": "$3.14", "baking potatoes": "$4.99", "lemon juiced": "$2.49", "cremini mushrooms": "$5.99", "almond flour": "$12.79", "dried navy beans": "$0.99", "medium potatoes": "$1.45", "salmon": "$24.99", "parsley": "$1.49", "Pillsbury\u00e2\u201e\u00a2 Crescent Recipe Creations\u00c2\u00ae refrigerated seamless dough sheet": "$4.49", "dried oregano": "$2.99", "chicken stock": "$2.99", "extra-virgin olive oil": "$6.99", "coriander": "$1.99", "chicken breasts": "$3.59", "extra large eggs": "$5.99", "small onion": "$1.13", "green curry paste": "$5.99", "sausages": "$5.99", "boneless skinless chicken breast": "$3.99", "boneless chicken breasts": "$5.99", "quinoa": "$7.99", "crushed red chili flakes": "$3.99", "yellow squash": "$0.80", "all purpose seasoning": "$5.49", "garlic salt": "$4.99", "ham": "$19.99", "cinnamon": "$5.49", "plain dry bread crumbs": "$2.89", "maple syrup": "$7.99", "avocado oil": "$12.99", "dried thyme": "$2.99", "italian style bread crumbs": "$2.89", "large tomato": "$2.99", "pizza sauce": "$3.99", "cooked chicken breast": "$13.99", "dried cranberries": "$4.99", "diced green chilies": "$1.99", "chopped fresh parsley": "$4.49", "lemon wedges": "$3.99", "sunflower seeds": "$3.69", "shredded cheese": "$4.99", "strawberries": "$5.99", "sparkling wine": "$4.99", "broccoli": "$3.14", "hot water": "$4.99", "orange bell pepper": "$1.07", "uncooked medium shrimp, peeled and deveined": "$9.99", "boneless, skinless chicken thighs": "$4.99", "red chili flakes": "$3.99", "ground cinnamon": "$5.49", "fresh orange juice": "$3.99", "bell peppers": "$1.02", "dried marjoram": "$3.29", "white fish fillet": "$19.99", "boneless, skinless chicken breasts": "$3.99", "chopped parsley": "$1.49", "egg": "$3.39", "white pepper": "$5.49", "white onion": "$1.12", "medium tomato": "$2.99", "fresh ginger": "$1.28", "grated Parmesan cheese": "$11.99", "unsalted butter": "$3.99", "cauliflower": "$3.99", "whole grain bread": "$6.99", "peeled shrimp": "$16.99", "beef broth": "$8.99", "boneless skinless chicken breasts": "$5.99", "granulated sugar": "$3.29", "hot sauce": "$6.39", "feta": "$7.99", "cilantro": "$7.99", "macaroni & cheese dinner": "$4.19", "vanilla": "$17.99", "frozen banana": "$5.99", "hummus": "$6.29", "diced tomatoes": "$2.99", "chickpeas": "$2.49", "large carrots": "$2.99", "fresh lime juice": "$4.99", "toasted sliced almonds": "$4.99", "large garlic cloves": "$7.49", "beef stock": "$8.99", "french fried onions": "$4.19", "ice cubes": "$4.99", "part-skim ricotta cheese": "$3.99", "salsa": "$5.99", "skin on salmon fillets": "$9.99", "shredded mozzarella": "$9.99", "white cheddar": "$10.99", "kale": "$6.92", "confectioners sugar": "$4.29", "refried beans": "$1.29", "cherry tomatoes": "$3.49", "cream of chicken soup": "$2.99", "ground beef": "$6.99", "spice": "$5.99", "dried parsley": "$4.49", "onion soup mix": "$3.99", "crushed red pepper flakes": "$3.99", "liquid smoke": "$6.29", "curry powder": "$5.49", "ranch salad dressing": "$3.49", "1/3-less-fat cream cheese": "$12.99", "frozen vegetables": "$3.99", "reduced-sodium soy sauce": "$5.29", "fresh cilantro": "$0.79", "onions": "$0.63", "fresh breadcrumbs": "$2.89", "ground flax seeds": "$3.99", "baby bella mushrooms": "$3.49", "black ground pepper": "$2.99", "frozen corn kernels": "$2.69", "saltine crackers": "$1.79", "Parmesan cheese": "$11.99", "cocoa powder": "$5.99", "oil": "$11.99", "provolone cheese": "$7.99", "dried basil leaves": "$4.99", "roasted tomatoes": "$2.49", "fresh ground black pepper": "$5.49", "bread crumbs": "$2.89", "cooked bacon": "$5.99", "green food coloring": "$6.99", "curry paste": "$5.99", "grated lemon zest": "$1.28", "whole grain mustard": "$3.99", "garlic paste": "$0.48", "garlic cloves": "$0.48", "butter lettuce": "$2.99", "rotini": "$3.99", "ground chipotle chile pepper": "$5.49", "shredded Italian cheese blend": "$4.99", "frozen peas": "$3.99", "extra virgin olive oil": "$6.99", "ripe bananas": "$0.19", "gala apple": "$0.64", "baking powder": "$1.99", "garlic clove": "$0.48", "baby spinach": "$4.69", "ground nutmeg": "$4.99", "all-purpose flour": "$3.29", "70% cacoa dark chocolate chips": "$3.99", "bay leaf": "$2.99", "less sodium chicken broth": "$6.29", "old-fashioned rolled oats": "$0.99", "Sriracha": "$4.99", "whole wheat pasta": "$4.99", "toasted sesame oil": "$3.69", "naan": "$5.99", "lean ground beef": "$6.99", "skirt steak": "$15.99", "lime juice": "$3.29", "I Can't Believe It's Not Butter!\u00c2\u00ae Spread": "$4.99", "fresh lemon juice": "$4.99", "almond milk": "$1.29", "Italian bread": "$1.99", "kidney beans": "$1.49", "red enchilada sauce": "$3.32", "soy sauce": "$4.49", "shredded Monterey Jack cheese": "$4.99", "corn tortillas": "$2.99", "1 jar (1 lb. 8 oz.) Ragu\u00c2\u00ae Old World Style\u00c2\u00ae Pasta Sauce, divided": "$6.99", "reduced fat sour cream": "$2.29", "andouille sausage": "$6.99", "sauce": "$6.99", "italian seasoning": "$3.99", "small eggplant": "$1.02", "light corn syrup": "$5.99", "brown sugar": "$3.79", "medjool date": "$7.99", "fresh tomatoes": "$3.99", "pesto": "$6.99", "chili powder": "$5.99", "green onions": "$0.89", "diced onion": "$1.13", "fresh thyme": "$2.99", "red bell pepper, sliced": "$0.82", "marinated artichoke hearts": "$4.99", "medium yellow onion": "$1.13", "Italian dressing": "$3.99", "pinto beans": "$2.29", "cornstarch": "$1.99", "frozen potatoes": "$3.99", "cider vinegar": "$2.99", "red wine vinegar": "$2.99", "sesame seeds": "$6.49", "sweet paprika": "$4.99", "baby potatoes": "$4.99", "ricotta cheese": "$3.99", "whole wheat naan": "$3.99", "frozen broccoli": "$2.69", "green bell pepper": "$1.02", "pure vanilla extract": "$17.99", "mini cucumbers": "$0.79", "potatoes": "$4.99", "flour tortillas": "$2.69", "Bertolli\u00c2\u00ae Alfredo Sauce": "$6.99", "fresh basil": "$2.99", "graham cracker crumbs": "$5.39", "corn": "$4.99", "garlic": "$2.79", "shredded rotisserie chicken": "$6.99", "sharp cheddar cheese": "$2.60", "flat leaf parsley": "$1.49", "baguette": "$2.69", "finely chopped fresh parsley": "$2.99", "frozen pizza dough": "$4.99", "cooking oil": "$7.99", "mirin": "$9.99", "apples": "$7.99", "dried pasta": "$8.29", "crushed tomatoes": "$1.69", "great northern beans": "$0.99", "noodles": "$8.49", "jack cheese": "$5.99", "summer squash": "$0.80", "1 jar (1 lb. 8 oz.) Ragu\u00c2\u00ae Old World Style\u00c2\u00ae Pasta Sauce": "$6.99", "chocolate chips": "$7.99", "bananas": "$0.19", "large eggs": "$3.99", "Haas avocado": "$3.99", "Tuscan kale": "$1.99", "challah bread": "$4.99", "lemon-lime soda": "$2.99", "quick cook parboiled brown rice": "$3.39", "cumin seeds": "$2.99", "pico de gallo": "$5.99", "boneless, skinless chicken breast halves": "$5.99", "red cabbage": "$3.46"}